mdi2img/__init__.py
mdi2img/__main__.py
mdi2img/bin/MDI2TIF.EXE
mdi2img/bin/MDTFCORE.DLL
mdi2img/bin/MDTFINK.DLL
mdi2img/bin/MSPTLS.DLL
mdi2img/bin/RICHED20.DLL
mdi2img/bin/ressource_link.txt
mdi2img/src/__init__.py
mdi2img/src/main.py
mdi2img/src/mdi_to_img.py
mdi2img/src/convert_to_any/__init__.py
mdi2img/src/convert_to_any/change_image_format.py
mdi2img/src/globals/__init__.py
mdi2img/src/globals/constants.py
mdi2img/src/globals/logo.py
mdi2img/src/img_to_tiff/__init__.py
mdi2img/src/img_to_tiff/mdi_to_tiff.py
mdi2img/src/viewer/__init__.py
mdi2img/src/viewer/view_image.py
mdi2img-1.0.2.dist-info/licenses/LICENSE
tests/__init__.py
tests/test_mdi_to_tiff.py
mdi2img-1.0.2.dist-info/METADATA
mdi2img-1.0.2.dist-info/WHEEL
mdi2img-1.0.2.dist-info/top_level.txt
mdi2img-1.0.2.dist-info/RECORD
