Metadata-Version: 2.4
Name: mdi2img
Version: 1.0.2
Summary: A module that allows you to convert mdi files to tiff and other formats
Home-page: https://github.com/Hanra-s-work/MDI2IMG
Author: Henry Letellier
Author-email: henrysoftwarehouse@protonmail.com
Classifier: Programming Language :: Python :: 3
Classifier: Operating System :: Microsoft :: Windows
License-File: LICENSE
Requires-Dist: flake8==7.3.0
Requires-Dist: pillow==11.3.0
Requires-Dist: display-tty==1.1.12
Requires-Dist: window-asset-tkinter==1.0.16
Dynamic: author
Dynamic: author-email
Dynamic: classifier
Dynamic: description
Dynamic: description-content-type
Dynamic: home-page
Dynamic: license-file
Dynamic: requires-dist
Dynamic: summary
